st_forna_component/.DS_Store
st_forna_component/02188894d5236b1517df3210b79c2a7f.svg
st_forna_component/__init__.py
st_forna_component/d3.js
st_forna_component/fa9b45d63b40299e0188927ca7d381a3.svg
st_forna_component/fornac.css
st_forna_component/fornac.css.map
st_forna_component/fornac.js
st_forna_component/fornac.js.LICENSE.txt
st_forna_component/fornac.js.map
st_forna_component/index.html
st_forna_component-1.0.1.dist-info/LICENSE
st_forna_component-1.0.1.dist-info/METADATA
st_forna_component-1.0.1.dist-info/WHEEL
st_forna_component-1.0.1.dist-info/top_level.txt
st_forna_component-1.0.1.dist-info/RECORD
